__init__.py
__main__.py
config.py
main.py
setup.py
gayybot-0.6.9.dist-info/LICENSE
gayybot-0.6.9.dist-info/METADATA
gayybot-0.6.9.dist-info/WHEEL
gayybot-0.6.9.dist-info/top_level.txt
gayybot-0.6.9.dist-info/RECORD
